zeek_reports/__init__.py
zeek_reports/cli.py
zeek_reports/notice_report.py
zeek_reports-0.1.7.dist-info/METADATA
zeek_reports-0.1.7.dist-info/WHEEL
zeek_reports-0.1.7.dist-info/entry_points.txt
zeek_reports-0.1.7.dist-info/top_level.txt
zeek_reports-0.1.7.dist-info/RECORD
