Metadata-Version: 2.4
Name: zeek-reports
Version: 0.1.7
Summary: Zeek notice reporting with CSV/JSON output and anomaly detection.
Author-email: ESS Security <security@esss.lu.se>
Requires-Python: >=3.6
Provides-Extra: dev
Requires-Dist: pytest; extra == "dev"
